asgimqtt/__init__.py
asgimqtt/cli.py
asgimqtt/server.py
asgimqtt-0.2.0.dist-info/DESCRIPTION.rst
asgimqtt-0.2.0.dist-info/METADATA
asgimqtt-0.2.0.dist-info/RECORD
asgimqtt-0.2.0.dist-info/WHEEL
asgimqtt-0.2.0.dist-info/entry_points.txt
asgimqtt-0.2.0.dist-info/metadata.json
asgimqtt-0.2.0.dist-info/top_level.txt
